[{"id":1034,"name":"Test16","price":10000,"createdDate":"May 14, 2019 11:38:15 PM","lastModifiedDate":"May 14, 2019 11:38:15 PM"},{"id":1035,"name":"Test16","price":10000,"createdDate":"May 14, 2019 11:38:21 PM","lastModifiedDate":"May 14, 2019 11:38:21 PM"},{"id":1036,"name":"Test16","price":10000,"createdDate":"May 14, 2019 11:38:22 PM","lastModifiedDate":"May 14, 2019 11:38:22 PM"},{"id":1037,"name":"Test16","price":10000,"createdDate":"May 14, 2019 11:38:23 PM","lastModifiedDate":"May 14, 2019 11:38:23 PM"}]